GT3/__init__.py
GT3/_version.py
GT3/constants.py
GT3/gt3.py
GT3/BeamDeposition/BeamDeposition.py
GT3/BeamDeposition/__init__.py
GT3/BeamDeposition/Functions/Beam.py
GT3/BeamDeposition/Functions/CalcPwrFrac.py
GT3/BeamDeposition/Functions/GetMFP.py
GT3/BeamDeposition/Functions/__init__.py
GT3/BeamDeposition/Processors/__init__.py
GT3/BeamDeposition/Test/DebugCore.py
GT3/BeamDeposition/Test/DebugInp.py
GT3/BeamDeposition/Test/SingleBeamTest.py
GT3/BeamDeposition/Test/__init__.py
GT3/Core/__init__.py
GT3/Core/core.py
GT3/Core/Functions/CalcChiJet.py
GT3/Core/Functions/CalcFSA.py
GT3/Core/Functions/CalcFsPerimInt.py
GT3/Core/Functions/CalcGrad.py
GT3/Core/Functions/CalcKappaElong.py
GT3/Core/Functions/CalcPsiNorm.py
GT3/Core/Functions/CalcPtsLines.py
GT3/Core/Functions/CalcRZ.py
GT3/Core/Functions/CalcRho2PsiInterp.py
GT3/Core/Functions/CalcSV.py
GT3/Core/Functions/CalcTheta1D.py
GT3/Core/Functions/CreateSurfAreaInterp.py
GT3/Core/Functions/CreateVolInterp.py
GT3/Core/Functions/Cut.py
GT3/Core/Functions/DrawCoreLine.py
GT3/Core/Functions/DrawCounterLine.py
GT3/Core/Functions/FindXPtMagAxis.py
GT3/Core/Functions/IsClose.py
GT3/Core/Functions/ProfileClasses.py
GT3/Core/Functions/__init__.py
GT3/Core/Functions/eVConvert.py
GT3/Core/Processors/__init__.py
GT3/Core/Processors/npencode.py
GT3/Core/Test/__init__.py
GT3/DensityLimit/__init__.py
GT3/DensityLimit/density_limit.py
GT3/DensityLimit/Functions/CalcQuadratic.py
GT3/DensityLimit/Functions/__init__.py
GT3/DensityLimit/Processors/__init__.py
GT3/DensityLimit/Test/__init__.py
GT3/Functions/GetNum.py
GT3/Functions/GetVals.py
GT3/Functions/__init__.py
GT3/IOL/__init__.py
GT3/IOL/iol.py
GT3/IOL/Functions/CalcIOLBeams.py
GT3/IOL/Functions/CalcIOLMaxwellian.py
GT3/IOL/Functions/CalcIOLMonoEn.py
GT3/IOL/Functions/CalcVSep.py
GT3/IOL/Functions/__init__.py
GT3/IOL/Processors/__init__.py
GT3/IOL/Test/__init__.py
GT3/ImpRadiation/__init__.py
GT3/ImpRadiation/imp_radiation.py
GT3/ImpRadiation/Functions/CombineObjs.py
GT3-0.0.3.dist-info/LICENSE
GT3-0.0.3.dist-info/METADATA
GT3-0.0.3.dist-info/WHEEL
GT3-0.0.3.dist-info/top_level.txt
GT3-0.0.3.dist-info/RECORD
