Metadata-Version: 2.1
Name: GT3
Version: 0.0.3
Summary: GT3 - The Georgia Tech Tokamak Transport codebase
Home-page: https://github.com/gt-frc/gt3/
Author: Maxwell D. Hill, Jonathan J. Roveto, Nicholas Piper
Author-email: max.hill@pm.me, veto1024@gmail.com, doom@gatech.edu
License: UNKNOWN
Platform: UNKNOWN
Classifier: Programming Language :: Python :: 3 :: Only
Classifier: Programming Language :: Python :: 3.8
Classifier: License :: OSI Approved :: MIT License
Classifier: Operating System :: OS Independent
Classifier: Development Status :: 4 - Beta
Classifier: Intended Audience :: Science/Research
Classifier: Natural Language :: English
Classifier: Topic :: Scientific/Engineering :: Physics
Requires-Python: >=3.8
Requires-Dist: matplotlib
Requires-Dist: multiprocess
Requires-Dist: scipy
Requires-Dist: numpy
Requires-Dist: pandas
Requires-Dist: pathos
Requires-Dist: Shapely
Requires-Dist: contours
Requires-Dist: enum34
Requires-Dist: PyYAML
Requires-Dist: texttable
Requires-Dist: deprecation
